LICENSE
MANIFEST.in
README.md
setup.py
coupon_management/__init__.py
coupon_management/actions.py
coupon_management/admin.py
coupon_management/apps.py
coupon_management/helpers.py
coupon_management/models.py
coupon_management/tests.py
coupon_management/validations.py
coupon_management/views.py
coupon_management/migrations/0001_initial.py
coupon_management/migrations/__init__.py
django_coupon_management.egg-info/PKG-INFO
django_coupon_management.egg-info/SOURCES.txt
django_coupon_management.egg-info/dependency_links.txt
django_coupon_management.egg-info/top_level.txt
docs/README.md
docs/models/Coupon.md
docs/models/Coupon_User.md
docs/models/Coupon_Validation.md
docs/models/Discount.md
docs/validation/Validations.md