Metadata-Version: 2.1
Name: django-coupon-management
Version: 1.1
Summary: A Django app that makes the use of coupon management and easy to handle
Home-page: https://github.com/krishnaansh/django-coupon-management
Download-URL: https://github.com/krishnaansh/django-coupon-management/archive/refs/tags/v1.1.zip
Author: Krishna
Author-email: krishnaansh997@gmail.com
License: MIT License
Keywords: django,coupon,management,coupon manage,promotion,django admin
Classifier: Environment :: Web Environment
Classifier: Framework :: Django :: 4.1
Classifier: Intended Audience :: Developers
Classifier: License :: OSI Approved :: MIT License
Classifier: Operating System :: OS Independent
Classifier: Programming Language :: Python :: 3
Classifier: Programming Language :: Python :: 3.6
Classifier: Programming Language :: Python :: 3.8
Classifier: Programming Language :: Python :: 3.10
Classifier: Topic :: Software Development :: Build Tools
Classifier: Topic :: Internet :: WWW/HTTP
Classifier: Topic :: Internet :: WWW/HTTP :: Dynamic Content
License-File: LICENSE
